pyidoit/__init__.py
pyidoit/client.py
pyidoit/exceptions.py
pyidoit/model.py
pyidoit/utils.py
pyidoit-0.0.2.dist-info/LICENSE
pyidoit-0.0.2.dist-info/METADATA
pyidoit-0.0.2.dist-info/WHEEL
pyidoit-0.0.2.dist-info/top_level.txt
pyidoit-0.0.2.dist-info/RECORD
